README.md
strainfish/__init__.py
strainfish/__main__.py
strainfish/cli.py
strainfish/commands/predict.py
strainfish/commands/train.py
strainfish/commands/version.py
strainfish/configs/__init__.py
strainfish/configs/imbalance_config.py
strainfish/configs/prediction_defaults.py
strainfish/configs/random_forest_config.py
strainfish/configs/sentencepiece_config.py
strainfish/configs/xgboost_config.py
strainfish/constants.py
strainfish/dynamic_cli_params.py
strainfish/encoder.py
strainfish/helpers.py
strainfish/logging_utils.py
strainfish/main.py
strainfish/models/StrainFish.cronobacter.rRNA.lbls.jl
strainfish/models/StrainFish.cronobacter.rRNA.nb.jl
strainfish/models/StrainFish.cronobacter.rRNA.rf.tl
strainfish/models/StrainFish.cronobacter.rRNA.tf.corpus.jl
strainfish/models/StrainFish.cronobacter.rRNA.xgb.ubj
strainfish/models/StrainFish.escherichia.rRNA.lbls.jl
strainfish/models/StrainFish.escherichia.rRNA.nb.jl
strainfish/models/StrainFish.escherichia.rRNA.rf.tl
strainfish/models/StrainFish.escherichia.rRNA.tf.corpus.jl
strainfish/models/StrainFish.escherichia.rRNA.xgb.ubj
strainfish/models.py
strainfish/predictor.py
strainfish/probabilities.py
strainfish/trainer.py
tests/README.md
tests/__init__.py
tests/sf_cli.py
tests/sf_integration.py
tests/sf_test_helpers.py
tests/test_input/predict.fasta
tests/test_input/test.train.csv
tests/test_input/test.train.fasta
tests/test_output/StrainFish_results.csv
tests/test_output/test_model.lbls.jl
tests/test_output/test_model.nb.jl
tests/test_output/test_model.rf.tl
tests/test_output/test_model.tf.corpus.jl
tests/test_output/test_model.xgb.ubj
strainfish-0.2.1.dist-info/LICENSE.md
strainfish-0.2.1.dist-info/METADATA
strainfish-0.2.1.dist-info/WHEEL
strainfish-0.2.1.dist-info/entry_points.txt
strainfish-0.2.1.dist-info/RECORD
