Metadata-Version: 2.3
Name: StrainFish
Version: 0.2.1
Summary: An Ensemble Machine Learning algorithm for classification of bacterial strains.
License: MIT
Author: Kranti.Konganti
Author-email: Kranti.Konganti@fda.hhs.gov
Requires-Python: >=3.11,<4.0
Classifier: License :: OSI Approved :: MIT License
Classifier: Programming Language :: Python :: 3
Classifier: Programming Language :: Python :: 3.11
Classifier: Programming Language :: Python :: 3.12
Classifier: Programming Language :: Python :: 3.13
Requires-Dist: biopython (>=1.85,<2.0)
Requires-Dist: cuml-cu12 (>=25.08,<26.0)
Requires-Dist: humanize (>=4.12.3,<5.0.0)
Requires-Dist: imbalanced-learn (>=0.14.0,<0.15.0)
Requires-Dist: importlib-metadata (>=8.7.0,<9.0.0)
Requires-Dist: joblib (>=1.4.2,<2.0.0)
Requires-Dist: numpy (>=2.2.3,<3.0.0)
Requires-Dist: pandas (>=2.2.3,<3.0.0)
Requires-Dist: psutil (>=6.1.1,<7.0.0)
Requires-Dist: pynvml (>=12.0,<13.0)
Requires-Dist: rich (>=14.1.0,<15.0.0)
Requires-Dist: rich-click (>=1.8.9,<2.0.0)
Requires-Dist: scikit-learn (>=1.6.1,<2.0.0)
Requires-Dist: sentencepiece (>=0.2.0,<0.3.0)
Requires-Dist: sourmash (>=4.9.4,<5.0.0)
Requires-Dist: treelite (>=4.4.1,<5.0.0)
Requires-Dist: xgboost (>=3.0.0,<4.0.0)
